{"id":"306","name":"石狩・空知・後志地方","caption":"20日5時札幌管区気象台発表の天気予報(今日20日から明後日22日まで)","areas":[{"area":"石狩地方","forecast":[{"date":"2020/4/20","dateJa":"今日20日","weather":"曇り後雨","weatherCode":"212","info":["南東の風 後 やや強く くもり 昼過ぎ から 雨","波 1メートル 後 1.5メートル"],"rain":[{"timeZone":"00-06","time":0,"rainyPercent":""},{"timeZone":"06-12","time":6,"rainyPercent":10},{"timeZone":"12-18","time":12,"rainyPercent":80},{"timeZone":"18-24","time":18,"rainyPercent":80}],"temp":[{"city":"札幌","min":"","max":11}]},{"date":"2020/4/21","dateJa":"明日21日","weather":"曇り一時雨","weatherCode":"202","info":["南の風 後 やや強く 海上 では 南の風 強く くもり 未明 雨","波 1.5メートル 後 4メートル"],"rain":[{"timeZone":"00-06","time":0,"rainyPercent":60},{"timeZone":"06-12","time":6,"rainyPercent":20},{"timeZone":"12-18","time":12,"rainyPercent":20},{"timeZone":"18-24","time":18,"rainyPercent":20}],"temp":[{"city":"札幌","min":7,"max":14}]}]},{"area":"空知地方","forecast":[{"date":"2020/4/20","dateJa":"今日20日","weather":"曇り後雨","weatherCode":"212","info":["南東の風 後 東の風 北空知 では 南東の風 やや強く くもり 夕方 から 雨"],"rain":[{"timeZone":"00-06","time":0,"rainyPercent":""},{"timeZone":"06-12","time":6,"rainyPercent":10},{"timeZone":"12-18","time":12,"rainyPercent":50},{"timeZone":"18-24","time":18,"rainyPercent":80}],"temp":[{"city":"岩見沢","min":"","max":12}]},{"date":"2020/4/21","dateJa":"明日21日","weather":"曇り一時雨","weatherCode":"202","info":["南の風 後 やや強く くもり 明け方 まで 雨 所により 夜遅く 雪"],"rain":[{"timeZone":"00-06","time":0,"rainyPercent":70},{"timeZone":"06-12","time":6,"rainyPercent":30},{"timeZone":"12-18","time":12,"rainyPercent":30},{"timeZone":"18-24","time":18,"rainyPercent":30}],"temp":[{"city":"岩見沢","min":6,"max":13}]}]},{"area":"後志地方","forecast":[{"date":"2020/4/20","dateJa":"今日20日","weather":"曇り後雨","weatherCode":"212","info":["東の風 後 南東の風 やや強く 海上 では 東の風 強く くもり 昼過ぎ から 雨","波 1メートル 後 1.5メートル"],"rain":[{"timeZone":"00-06","time":0,"rainyPercent":""},{"timeZone":"06-12","time":6,"rainyPercent":20},{"timeZone":"12-18","time":12,"rainyPercent":80},{"timeZone":"18-24","time":18,"rainyPercent":90}],"temp":[{"city":"倶知安","min":"","max":9}]},{"date":"2020/4/21","dateJa":"明日21日","weather":"曇り一時雨","weatherCode":"202","info":["南西の風 後 やや強く 海上 では 南の風 強く くもり 明け方 まで 雨","波 1.5メートル 後 4メートル"],"rain":[{"timeZone":"00-06","time":0,"rainyPercent":60},{"timeZone":"06-12","time":6,"rainyPercent":30},{"timeZone":"12-18","time":12,"rainyPercent":30},{"timeZone":"18-24","time":18,"rainyPercent":30}],"temp":[{"city":"倶知安","min":7,"max":11}]}]}]}