{"id":"307","name":"渡島・檜山地方","caption":"2日17時函館地方気象台発表の天気予報(今日2日から明後日4日まで)","areas":[{"area":"渡島地方","forecast":[{"date":"2021/1/2","dateJa":"今夜2日","weather":"曇り","weatherCode":"200","info":["北西の風 後 西の風 渡島西部 では 北西の風 やや強く くもり 所により 雪 で ふぶく","波 3メートル"],"rain":[{"timeZone":"00-06","time":0,"rainyPercent":""},{"timeZone":"06-12","time":6,"rainyPercent":""},{"timeZone":"12-18","time":12,"rainyPercent":""},{"timeZone":"18-24","time":18,"rainyPercent":20}],"temp":[]},{"date":"2021/1/3","dateJa":"明日3日","weather":"曇り後一時雪","weatherCode":"215","info":["西の風 渡島西部 では 西の風 やや強く くもり 夜 雪","波 2.5メートル"],"rain":[{"timeZone":"00-06","time":0,"rainyPercent":10},{"timeZone":"06-12","time":6,"rainyPercent":20},{"timeZone":"12-18","time":12,"rainyPercent":20},{"timeZone":"18-24","time":18,"rainyPercent":40}],"temp":[{"city":"函館","min":-10,"max":-3}]},{"date":"2021/1/4","dateJa":"明後日4日","weather":"曇り一時雪","weatherCode":"204","info":["西の風 くもり 一時 雪","波 2.5メートル"],"rain":[],"temp":[]}]},{"area":"檜山地方","forecast":[{"date":"2021/1/2","dateJa":"今夜2日","weather":"雪後曇り","weatherCode":"413","info":["西の風 やや強く 雪 で ふぶく 夜遅く くもり","波 3メートル"],"rain":[{"timeZone":"00-06","time":0,"rainyPercent":""},{"timeZone":"06-12","time":6,"rainyPercent":""},{"timeZone":"12-18","time":12,"rainyPercent":""},{"timeZone":"18-24","time":18,"rainyPercent":30}],"temp":[]},{"date":"2021/1/3","dateJa":"明日3日","weather":"曇り時々雪","weatherCode":"204","info":["西の風 やや強く くもり 時々 雪 で ふぶく","波 2.5メートル"],"rain":[{"timeZone":"00-06","time":0,"rainyPercent":20},{"timeZone":"06-12","time":6,"rainyPercent":30},{"timeZone":"12-18","time":12,"rainyPercent":30},{"timeZone":"18-24","time":18,"rainyPercent":40}],"temp":[{"city":"江差","min":-6,"max":-2}]},{"date":"2021/1/4","dateJa":"明後日4日","weather":"曇り一時雪","weatherCode":"204","info":["西の風 やや強く くもり 一時 雪 で ふぶく","波 2.5メートル"],"rain":[],"temp":[]}]}]}