{"id":"310","name":"岩手県","caption":"4日5時盛岡地方気象台発表の天気予報(今日4日から明後日6日まで)","areas":[{"area":"内陸","forecast":[{"date":"2020/7/4","dateJa":"今日4日","weather":"雨後曇り","weatherCode":"313","info":["南の風 日中 北の風 雨 夜 くもり"],"rain":[{"timeZone":"00-06","time":0,"rainyPercent":""},{"timeZone":"06-12","time":6,"rainyPercent":80},{"timeZone":"12-18","time":12,"rainyPercent":80},{"timeZone":"18-24","time":18,"rainyPercent":30}],"temp":[{"city":"盛岡","min":"","max":21},{"city":"二戸","min":"","max":20},{"city":"一関","min":"","max":23}]},{"date":"2020/7/5","dateJa":"明日5日","weather":"曇り","weatherCode":"200","info":["南の風 日中 南西の風 くもり 所により 雨"],"rain":[{"timeZone":"00-06","time":0,"rainyPercent":20},{"timeZone":"06-12","time":6,"rainyPercent":20},{"timeZone":"12-18","time":12,"rainyPercent":40},{"timeZone":"18-24","time":18,"rainyPercent":40}],"temp":[{"city":"盛岡","min":18,"max":27},{"city":"二戸","min":15,"max":25},{"city":"一関","min":18,"max":28}]}]},{"area":"沿岸北部","forecast":[{"date":"2020/7/4","dateJa":"今日4日","weather":"雨時々止む","weatherCode":"302","info":["北東の風 海上 では 南東の風 やや強く 雨 朝晩 くもり","波 1.5メートル"],"rain":[{"timeZone":"00-06","time":0,"rainyPercent":""},{"timeZone":"06-12","time":6,"rainyPercent":70},{"timeZone":"12-18","time":12,"rainyPercent":80},{"timeZone":"18-24","time":18,"rainyPercent":30}],"temp":[{"city":"宮古","min":"","max":19}]},{"date":"2020/7/5","dateJa":"明日5日","weather":"曇り","weatherCode":"200","info":["西の風 日中 北東の風 くもり 所により 夕方 から 雨","波 2メートル 後 1.5メートル"],"rain":[{"timeZone":"00-06","time":0,"rainyPercent":10},{"timeZone":"06-12","time":6,"rainyPercent":10},{"timeZone":"12-18","time":12,"rainyPercent":20},{"timeZone":"18-24","time":18,"rainyPercent":40}],"temp":[{"city":"宮古","min":15,"max":21}]}]},{"area":"沿岸南部","forecast":[{"date":"2020/7/4","dateJa":"今日4日","weather":"雨後曇り","weatherCode":"313","info":["東の風 後 北東の風 海上 では 東の風 やや強く 雨 夜 くもり","波 1.5メートル 後 2メートル"],"rain":[{"timeZone":"00-06","time":0,"rainyPercent":""},{"timeZone":"06-12","time":6,"rainyPercent":90},{"timeZone":"12-18","time":12,"rainyPercent":70},{"timeZone":"18-24","time":18,"rainyPercent":20}],"temp":[{"city":"大船渡","min":"","max":22}]},{"date":"2020/7/5","dateJa":"明日5日","weather":"曇り","weatherCode":"200","info":["南の風 くもり 所により 夕方 から 雨","波 2メートル"],"rain":[{"timeZone":"00-06","time":0,"rainyPercent":10},{"timeZone":"06-12","time":6,"rainyPercent":10},{"timeZone":"12-18","time":12,"rainyPercent":30},{"timeZone":"18-24","time":18,"rainyPercent":40}],"temp":[{"city":"大船渡","min":17,"max":26}]}]}]}