{"id":"315","name":"群馬県","caption":"20日5時前橋地方気象台発表の天気予報(今日20日から明後日22日まで)","areas":[{"area":"南部","forecast":[{"date":"2020/7/20","dateJa":"今日20日","weather":"曇り","weatherCode":"200","info":["北西の風 日中 南東の風 くもり 所により 昼過ぎ から 雨 で 雷を伴う"],"rain":[{"timeZone":"00-06","time":0,"rainyPercent":""},{"timeZone":"06-12","time":6,"rainyPercent":20},{"timeZone":"12-18","time":12,"rainyPercent":40},{"timeZone":"18-24","time":18,"rainyPercent":30}],"temp":[{"city":"前橋","min":"","max":29}]},{"date":"2020/7/21","dateJa":"明日21日","weather":"曇り","weatherCode":"200","info":["南東の風 くもり 所により 朝 から 雨 で 雷を伴う"],"rain":[{"timeZone":"00-06","time":0,"rainyPercent":10},{"timeZone":"06-12","time":6,"rainyPercent":30},{"timeZone":"12-18","time":12,"rainyPercent":30},{"timeZone":"18-24","time":18,"rainyPercent":30}],"temp":[{"city":"前橋","min":22,"max":27}]}]},{"area":"北部","forecast":[{"date":"2020/7/20","dateJa":"今日20日","weather":"曇り","weatherCode":"200","info":["北の風 日中 南の風 くもり 所により 昼過ぎ から 雨 で 雷を伴う"],"rain":[{"timeZone":"00-06","time":0,"rainyPercent":""},{"timeZone":"06-12","time":6,"rainyPercent":20},{"timeZone":"12-18","time":12,"rainyPercent":40},{"timeZone":"18-24","time":18,"rainyPercent":30}],"temp":[{"city":"みなかみ","min":"","max":25}]},{"date":"2020/7/21","dateJa":"明日21日","weather":"曇り","weatherCode":"200","info":["南の風 くもり 所により 朝 から 雨 で 雷を伴う"],"rain":[{"timeZone":"00-06","time":0,"rainyPercent":20},{"timeZone":"06-12","time":6,"rainyPercent":40},{"timeZone":"12-18","time":12,"rainyPercent":40},{"timeZone":"18-24","time":18,"rainyPercent":30}],"temp":[{"city":"みなかみ","min":19,"max":25}]}]}]}