{"id":"318","name":"千葉県","caption":"28日17時銚子地方気象台発表の天気予報(今日28日から明後日1日まで)","areas":[{"area":"北西部","forecast":[{"date":"2020/2/28","dateJa":"今夜28日","weather":"曇り","weatherCode":"200","info":["南の風 後 南東の風 くもり","波 0.5メートル"],"rain":[{"timeZone":"00-06","time":0,"rainyPercent":""},{"timeZone":"06-12","time":6,"rainyPercent":""},{"timeZone":"12-18","time":12,"rainyPercent":""},{"timeZone":"18-24","time":18,"rainyPercent":10}],"temp":[]},{"date":"2020/2/29","dateJa":"明日29日","weather":"曇り","weatherCode":"200","info":["北の風 後 南西の風 くもり 昼過ぎ 晴れ 所により 朝 まで 雨","波 0.5メートル"],"rain":[{"timeZone":"00-06","time":0,"rainyPercent":20},{"timeZone":"06-12","time":6,"rainyPercent":20},{"timeZone":"12-18","time":12,"rainyPercent":10},{"timeZone":"18-24","time":18,"rainyPercent":20}],"temp":[{"city":"千葉","min":5,"max":13}]},{"date":"2020/3/1","dateJa":"明後日1日","weather":"曇り","weatherCode":"200","info":["北の風 後 東の風 くもり","波 0.5メートル"],"rain":[],"temp":[]}]},{"area":"北東部","forecast":[{"date":"2020/2/28","dateJa":"今夜28日","weather":"曇り","weatherCode":"200","info":["南の風 後 南西の風 くもり","波 2メートル 後 1.5メートル うねり を伴う"],"rain":[{"timeZone":"00-06","time":0,"rainyPercent":""},{"timeZone":"06-12","time":6,"rainyPercent":""},{"timeZone":"12-18","time":12,"rainyPercent":""},{"timeZone":"18-24","time":18,"rainyPercent":10}],"temp":[]},{"date":"2020/2/29","dateJa":"明日29日","weather":"曇り","weatherCode":"200","info":["東の風 後 南西の風 海上 では 後 南西の風 やや強く くもり 昼過ぎ 晴れ 所により 朝 まで 雨","波 1.5メートル うねり を伴う"],"rain":[{"timeZone":"00-06","time":0,"rainyPercent":30},{"timeZone":"06-12","time":6,"rainyPercent":30},{"timeZone":"12-18","time":12,"rainyPercent":10},{"timeZone":"18-24","time":18,"rainyPercent":20}],"temp":[{"city":"銚子","min":4,"max":12}]},{"date":"2020/3/1","dateJa":"明後日1日","weather":"曇り","weatherCode":"200","info":["北の風 後 北東の風 くもり","波 1.5メートル うねり を伴う"],"rain":[],"temp":[]}]},{"area":"南部","forecast":[{"date":"2020/2/28","dateJa":"今夜28日","weather":"曇り","weatherCode":"200","info":["南の風 後 南西の風 くもり","波 2メートル 後 1.5メートル うねり を伴う"],"rain":[{"timeZone":"00-06","time":0,"rainyPercent":""},{"timeZone":"06-12","time":6,"rainyPercent":""},{"timeZone":"12-18","time":12,"rainyPercent":""},{"timeZone":"18-24","time":18,"rainyPercent":10}],"temp":[]},{"date":"2020/2/29","dateJa":"明日29日","weather":"曇り","weatherCode":"200","info":["北の風 後 南西の風 夷隅・安房 では 後 南西の風 やや強く くもり 昼過ぎ 晴れ 所により 朝晩 雨","波 1.5メートル うねり を伴う"],"rain":[{"timeZone":"00-06","time":0,"rainyPercent":40},{"timeZone":"06-12","time":6,"rainyPercent":30},{"timeZone":"12-18","time":12,"rainyPercent":10},{"timeZone":"18-24","time":18,"rainyPercent":30}],"temp":[{"city":"館山","min":3,"max":14}]},{"date":"2020/3/1","dateJa":"明後日1日","weather":"曇り一時雨","weatherCode":"202","info":["北の風 後 東の風 くもり 一時 雨","波 1.5メートル うねり を伴う"],"rain":[],"temp":[]}]}]}