{"id":"324","name":"富山県","caption":"20日17時富山地方気象台発表の天気予報(今日20日から明後日22日まで)","areas":[{"area":"東部","forecast":[{"date":"2020/3/20","dateJa":"今夜20日","weather":"曇り","weatherCode":"200","info":["南西の風 やや強く 後 南の風 東部北 では 南西の風 強く くもり 所により 夕方 雨か雪","波 3メートル うねり を伴う"],"rain":[{"timeZone":"00-06","time":0,"rainyPercent":""},{"timeZone":"06-12","time":6,"rainyPercent":""},{"timeZone":"12-18","time":12,"rainyPercent":""},{"timeZone":"18-24","time":18,"rainyPercent":20}],"temp":[]},{"date":"2020/3/21","dateJa":"明日21日","weather":"晴れ後曇り","weatherCode":"110","info":["南の風 後 南西の風 やや強く 東部北 では はじめ 南西の風 強く 晴れ 昼過ぎ から くもり 所により 夕方 から 夜のはじめ頃 雨","波 3メートル 後 1メートル うねり を伴う"],"rain":[{"timeZone":"00-06","time":0,"rainyPercent":10},{"timeZone":"06-12","time":6,"rainyPercent":10},{"timeZone":"12-18","time":12,"rainyPercent":30},{"timeZone":"18-24","time":18,"rainyPercent":30}],"temp":[{"city":"富山","min":6,"max":18}]},{"date":"2020/3/22","dateJa":"明後日22日","weather":"曇り一時雨","weatherCode":"202","info":["南の風 後 北東の風 くもり 一時 雨","波 1メートル"],"rain":[],"temp":[]}]},{"area":"西部","forecast":[{"date":"2020/3/20","dateJa":"今夜20日","weather":"曇り","weatherCode":"200","info":["南西の風 やや強く くもり","波 1メートル"],"rain":[{"timeZone":"00-06","time":0,"rainyPercent":""},{"timeZone":"06-12","time":6,"rainyPercent":""},{"timeZone":"12-18","time":12,"rainyPercent":""},{"timeZone":"18-24","time":18,"rainyPercent":10}],"temp":[]},{"date":"2020/3/21","dateJa":"明日21日","weather":"晴れ後曇り","weatherCode":"110","info":["南西の風 日中 やや強く 晴れ 昼過ぎ から くもり 所により 夕方 雨","波 1メートル"],"rain":[{"timeZone":"00-06","time":0,"rainyPercent":10},{"timeZone":"06-12","time":6,"rainyPercent":10},{"timeZone":"12-18","time":12,"rainyPercent":30},{"timeZone":"18-24","time":18,"rainyPercent":20}],"temp":[{"city":"伏木","min":4,"max":17}]},{"date":"2020/3/22","dateJa":"明後日22日","weather":"曇り一時雨","weatherCode":"202","info":["南西の風 後 北東の風 くもり 一時 雨","波 0.5メートル"],"rain":[],"temp":[]}]}]}