{"id":"324","name":"富山県","caption":"4日17時富山地方気象台発表の天気予報(今日4日から明後日6日まで)","areas":[{"area":"東部","forecast":[{"date":"2020/2/4","dateJa":"今夜4日","weather":"晴れ後雨か雪","weatherCode":"708","info":["南西の風 海上 では 南西の風 やや強く 晴れ 夜 雨か雪 所により 雷 を伴う","波 1メートル"],"rain":[{"timeZone":"00-06","time":0,"rainyPercent":""},{"timeZone":"06-12","time":6,"rainyPercent":""},{"timeZone":"12-18","time":12,"rainyPercent":""},{"timeZone":"18-24","time":18,"rainyPercent":50}],"temp":[]},{"date":"2020/2/5","dateJa":"明日5日","weather":"雪か雨","weatherCode":"400","info":["南西の風 やや強く 後 西の風 海上 では 南西の風 強く 雪か雨 所により 夕方 まで 雷 を伴う","波 1メートル 後 3メートル"],"rain":[{"timeZone":"00-06","time":0,"rainyPercent":50},{"timeZone":"06-12","time":6,"rainyPercent":90},{"timeZone":"12-18","time":12,"rainyPercent":90},{"timeZone":"18-24","time":18,"rainyPercent":80}],"temp":[{"city":"富山","min":3,"max":7}]},{"date":"2020/2/6","dateJa":"明後日6日","weather":"雪時々止む","weatherCode":"402","info":["南西の風 後 南の風 雪 時々 くもり","波 3メートル 後 2メートル うねり を伴う"],"rain":[],"temp":[]}]},{"area":"西部","forecast":[{"date":"2020/2/4","dateJa":"今夜4日","weather":"晴れ後雨か雪","weatherCode":"708","info":["南西の風 海上 では 南西の風 やや強く 晴れ 夜 雨か雪 所により 雷 を伴う","波 1メートル 後 0.5メートル"],"rain":[{"timeZone":"00-06","time":0,"rainyPercent":""},{"timeZone":"06-12","time":6,"rainyPercent":""},{"timeZone":"12-18","time":12,"rainyPercent":""},{"timeZone":"18-24","time":18,"rainyPercent":50}],"temp":[]},{"date":"2020/2/5","dateJa":"明日5日","weather":"雪か雨","weatherCode":"400","info":["南西の風 やや強く 後 西の風 海上 では 南西の風 強く 雪か雨 所により 夕方 まで 雷 を伴う","波 0.5メートル 後 1メートル"],"rain":[{"timeZone":"00-06","time":0,"rainyPercent":50},{"timeZone":"06-12","time":6,"rainyPercent":90},{"timeZone":"12-18","time":12,"rainyPercent":90},{"timeZone":"18-24","time":18,"rainyPercent":80}],"temp":[{"city":"伏木","min":3,"max":7}]},{"date":"2020/2/6","dateJa":"明後日6日","weather":"雪時々止む","weatherCode":"402","info":["南西の風 雪 時々 くもり","波 1.5メートル うねり を伴う"],"rain":[],"temp":[]}]}]}