{"id":"325","name":"石川県","caption":"22日17時金沢地方気象台発表の天気予報(今日22日から明後日24日まで)","areas":[{"area":"加賀","forecast":[{"date":"2020/8/22","dateJa":"今夜22日","weather":"曇り後晴れ","weatherCode":"710","info":["北東の風 後 東の風 くもり 夜遅く 晴れ 所により 夜のはじめ頃 まで 雨 で 雷を伴う","波 1メートル"],"rain":[{"timeZone":"00-06","time":0,"rainyPercent":""},{"timeZone":"06-12","time":6,"rainyPercent":""},{"timeZone":"12-18","time":12,"rainyPercent":""},{"timeZone":"18-24","time":18,"rainyPercent":20}],"temp":[]},{"date":"2020/8/23","dateJa":"明日23日","weather":"曇り後一時雨","weatherCode":"212","info":["東の風 日中 北東の風 くもり 時々 晴れ 夕方 一時 雨 所により 夕方 から 夜のはじめ頃 雷を伴い 激しく 降る","波 0.5メートル 後 1メートル"],"rain":[{"timeZone":"00-06","time":0,"rainyPercent":10},{"timeZone":"06-12","time":6,"rainyPercent":20},{"timeZone":"12-18","time":12,"rainyPercent":50},{"timeZone":"18-24","time":18,"rainyPercent":30}],"temp":[{"city":"金沢","min":26,"max":32}]},{"date":"2020/8/24","dateJa":"明後日24日","weather":"晴れ時々曇り","weatherCode":"101","info":["東の風 後 北の風 晴れ 時々 くもり","波 0.5メートル"],"rain":[],"temp":[]}]},{"area":"能登","forecast":[{"date":"2020/8/22","dateJa":"今夜22日","weather":"曇り後晴れ","weatherCode":"710","info":["北東の風 くもり 夜遅く 晴れ","波 1メートル"],"rain":[{"timeZone":"00-06","time":0,"rainyPercent":""},{"timeZone":"06-12","time":6,"rainyPercent":""},{"timeZone":"12-18","time":12,"rainyPercent":""},{"timeZone":"18-24","time":18,"rainyPercent":10}],"temp":[]},{"date":"2020/8/23","dateJa":"明日23日","weather":"曇り時々晴れ","weatherCode":"201","info":["北東の風 日中 北の風 くもり 時々 晴れ 所により 昼過ぎ から 雨 で 雷を伴う","波 0.5メートル 後 1メートル"],"rain":[{"timeZone":"00-06","time":0,"rainyPercent":10},{"timeZone":"06-12","time":6,"rainyPercent":10},{"timeZone":"12-18","time":12,"rainyPercent":30},{"timeZone":"18-24","time":18,"rainyPercent":20}],"temp":[{"city":"輪島","min":24,"max":29}]},{"date":"2020/8/24","dateJa":"明後日24日","weather":"晴れ時々曇り","weatherCode":"101","info":["北東の風 晴れ 時々 くもり","波 0.5メートル"],"rain":[],"temp":[]}]}]}