{"id":"327","name":"静岡県","caption":"26日5時静岡地方気象台発表の天気予報(今日26日から明後日28日まで)","areas":[{"area":"中部","forecast":[{"date":"2019/12/26","dateJa":"今日26日","weather":"曇り時々雨","weatherCode":"202","info":["西の風 後 北の風 海上 では 後 南の風 やや強く くもり 時々 雨","波 1.5メートル 後 2メートル"],"rain":[{"timeZone":"00-06","time":0,"rainyPercent":""},{"timeZone":"06-12","time":6,"rainyPercent":50},{"timeZone":"12-18","time":12,"rainyPercent":40},{"timeZone":"18-24","time":18,"rainyPercent":80}],"temp":[{"city":"静岡","min":"","max":14}]},{"date":"2019/12/27","dateJa":"明日27日","weather":"晴れ一時雨","weatherCode":"102","info":["西の風 強く 後 やや強く 海上 では 西の風 非常に強く 晴れ 明け方 まで 雨","波 4メートル 後 2.5メートル"],"rain":[{"timeZone":"00-06","time":0,"rainyPercent":70},{"timeZone":"06-12","time":6,"rainyPercent":0},{"timeZone":"12-18","time":12,"rainyPercent":0},{"timeZone":"18-24","time":18,"rainyPercent":0}],"temp":[{"city":"静岡","min":9,"max":16}]}]},{"area":"伊豆","forecast":[{"date":"2019/12/26","dateJa":"今日26日","weather":"曇り時々雨","weatherCode":"202","info":["東の風 伊豆南 では 後 南の風 やや強く くもり 時々 雨","波 1.5メートル 後 2メートル"],"rain":[{"timeZone":"00-06","time":0,"rainyPercent":""},{"timeZone":"06-12","time":6,"rainyPercent":50},{"timeZone":"12-18","time":12,"rainyPercent":40},{"timeZone":"18-24","time":18,"rainyPercent":60}],"temp":[{"city":"網代","min":"","max":12},{"city":"石廊崎","min":"","max":14}]},{"date":"2019/12/27","dateJa":"明日27日","weather":"晴れ一時雨","weatherCode":"102","info":["西の風 強く 後 やや強く 伊豆南 では 西の風 非常に強く 晴れ 明け方 まで 雨","波 4メートル 後 2.5メートル"],"rain":[{"timeZone":"00-06","time":0,"rainyPercent":60},{"timeZone":"06-12","time":6,"rainyPercent":0},{"timeZone":"12-18","time":12,"rainyPercent":0},{"timeZone":"18-24","time":18,"rainyPercent":0}],"temp":[{"city":"網代","min":10,"max":15},{"city":"石廊崎","min":13,"max":15}]}]},{"area":"東部","forecast":[{"date":"2019/12/26","dateJa":"今日26日","weather":"曇り時々雨","weatherCode":"202","info":["東の風 くもり 時々 雨","波 1メートル"],"rain":[{"timeZone":"00-06","time":0,"rainyPercent":""},{"timeZone":"06-12","time":6,"rainyPercent":50},{"timeZone":"12-18","time":12,"rainyPercent":30},{"timeZone":"18-24","time":18,"rainyPercent":60}],"temp":[{"city":"三島","min":"","max":14}]},{"date":"2019/12/27","dateJa":"明日27日","weather":"晴れ一時雨","weatherCode":"102","info":["西の風 海上 では 西の風 やや強く 晴れ 明け方 まで 雨","波 2メートル 後 1メートル"],"rain":[{"timeZone":"00-06","time":0,"rainyPercent":70},{"timeZone":"06-12","time":6,"rainyPercent":0},{"timeZone":"12-18","time":12,"rainyPercent":0},{"timeZone":"18-24","time":18,"rainyPercent":0}],"temp":[{"city":"三島","min":8,"max":15}]}]},{"area":"西部","forecast":[{"date":"2019/12/26","dateJa":"今日26日","weather":"曇り時々雨","weatherCode":"202","info":["北の風 後 北東の風 海上 では 後 南の風 やや強く くもり 時々 雨","波 1.5メートル 後 2メートル"],"rain":[{"timeZone":"00-06","time":0,"rainyPercent":""},{"timeZone":"06-12","time":6,"rainyPercent":50},{"timeZone":"12-18","time":12,"rainyPercent":40},{"timeZone":"18-24","time":18,"rainyPercent":70}],"temp":[{"city":"浜松","min":"","max":13},{"city":"御前崎","min":"","max":13}]},{"date":"2019/12/27","dateJa":"明日27日","weather":"晴れ一時雨","weatherCode":"102","info":["西の風 強く 後 やや強く 海上 では 北西の風 非常に強く 晴れ 未明 雨","波 4メートル 後 2.5メートル"],"rain":[{"timeZone":"00-06","time":0,"rainyPercent":70},{"timeZone":"06-12","time":6,"rainyPercent":0},{"timeZone":"12-18","time":12,"rainyPercent":0},{"timeZone":"18-24","time":18,"rainyPercent":0}],"temp":[{"city":"浜松","min":10,"max":13},{"city":"御前崎","min":11,"max":14}]}]}]}