{"id":"328","name":"岐阜県","caption":"9日17時岐阜地方気象台発表の天気予報(今日9日から明後日11日まで)","areas":[{"area":"美濃地方","forecast":[{"date":"2021/2/9","dateJa":"今夜9日","weather":"晴れ後曇り","weatherCode":"707","info":["西の風 晴れ 夜遅く くもり"],"rain":[{"timeZone":"00-06","time":0,"rainyPercent":""},{"timeZone":"06-12","time":6,"rainyPercent":""},{"timeZone":"12-18","time":12,"rainyPercent":""},{"timeZone":"18-24","time":18,"rainyPercent":10}],"temp":[]},{"date":"2021/2/10","dateJa":"明日10日","weather":"曇り時々晴れ","weatherCode":"201","info":["北の風 後 西の風 くもり 時々 晴れ 所により 夜 雪か雨 で 雷を伴う"],"rain":[{"timeZone":"00-06","time":0,"rainyPercent":10},{"timeZone":"06-12","time":6,"rainyPercent":10},{"timeZone":"12-18","time":12,"rainyPercent":10},{"timeZone":"18-24","time":18,"rainyPercent":30}],"temp":[{"city":"岐阜","min":1,"max":11}]},{"date":"2021/2/11","dateJa":"明後日11日","weather":"晴れ時々曇り","weatherCode":"101","info":["北西の風 後 西の風 晴れ 時々 くもり"],"rain":[],"temp":[]}]},{"area":"飛騨地方","forecast":[{"date":"2021/2/9","dateJa":"今夜9日","weather":"曇り","weatherCode":"200","info":["北の風 後 北東の風 くもり"],"rain":[{"timeZone":"00-06","time":0,"rainyPercent":""},{"timeZone":"06-12","time":6,"rainyPercent":""},{"timeZone":"12-18","time":12,"rainyPercent":""},{"timeZone":"18-24","time":18,"rainyPercent":20}],"temp":[]},{"date":"2021/2/10","dateJa":"明日10日","weather":"曇り後一時雪","weatherCode":"215","info":["北の風 後 東の風 くもり 夜遅く 雪 飛騨北部 では 雷 を伴う"],"rain":[{"timeZone":"00-06","time":0,"rainyPercent":10},{"timeZone":"06-12","time":6,"rainyPercent":10},{"timeZone":"12-18","time":12,"rainyPercent":10},{"timeZone":"18-24","time":18,"rainyPercent":50}],"temp":[{"city":"高山","min":-6,"max":5}]},{"date":"2021/2/11","dateJa":"明後日11日","weather":"晴れ一時雪","weatherCode":"104","info":["北の風 晴れ 一時 雪"],"rain":[],"temp":[]}]}]}