{"id":"333","name":"京都府","caption":"29日17時京都地方気象台発表の天気予報(今日29日から明後日1日まで)","areas":[{"area":"南部","forecast":[{"date":"2020/9/29","dateJa":"今夜29日","weather":"曇り時々晴れ","weatherCode":"704","info":["北東の風 後 北の風 くもり 夜のはじめ頃 晴れ"],"rain":[{"timeZone":"00-06","time":0,"rainyPercent":""},{"timeZone":"06-12","time":6,"rainyPercent":""},{"timeZone":"12-18","time":12,"rainyPercent":""},{"timeZone":"18-24","time":18,"rainyPercent":0}],"temp":[]},{"date":"2020/9/30","dateJa":"明日30日","weather":"曇り後一時雨","weatherCode":"212","info":["北の風 日中 北西の風 くもり 夕方 一時 雨 所により 昼過ぎ から 雷 を伴う"],"rain":[{"timeZone":"00-06","time":0,"rainyPercent":0},{"timeZone":"06-12","time":6,"rainyPercent":30},{"timeZone":"12-18","time":12,"rainyPercent":60},{"timeZone":"18-24","time":18,"rainyPercent":40}],"temp":[{"city":"京都","min":18,"max":27}]},{"date":"2020/10/1","dateJa":"明後日1日","weather":"曇り後晴れ","weatherCode":"210","info":["北西の風 後 北の風 くもり 後 晴れ"],"rain":[],"temp":[]}]},{"area":"北部","forecast":[{"date":"2020/9/29","dateJa":"今夜29日","weather":"曇り時々晴れ","weatherCode":"704","info":["北の風 くもり 夜のはじめ頃 晴れ","波 1メートル"],"rain":[{"timeZone":"00-06","time":0,"rainyPercent":""},{"timeZone":"06-12","time":6,"rainyPercent":""},{"timeZone":"12-18","time":12,"rainyPercent":""},{"timeZone":"18-24","time":18,"rainyPercent":0}],"temp":[]},{"date":"2020/9/30","dateJa":"明日30日","weather":"曇り後雨","weatherCode":"212","info":["北東の風 後 北の風 くもり 夕方 から 雨 所により 昼過ぎ から 雷 を伴う","波 1メートル"],"rain":[{"timeZone":"00-06","time":0,"rainyPercent":10},{"timeZone":"06-12","time":6,"rainyPercent":40},{"timeZone":"12-18","time":12,"rainyPercent":60},{"timeZone":"18-24","time":18,"rainyPercent":60}],"temp":[{"city":"舞鶴","min":15,"max":25}]},{"date":"2020/10/1","dateJa":"明後日1日","weather":"曇り後晴れ","weatherCode":"210","info":["北の風 くもり 後 晴れ","波 1メートル"],"rain":[],"temp":[]}]}]}