{"id":"341","name":"香川県","caption":"29日11時高松地方気象台発表の天気予報(今日29日から明後日31日まで)","areas":[{"area":"香川県","forecast":[{"date":"2019/7/29","dateJa":"今日29日","weather":"晴れ時々曇り","weatherCode":"101","info":["北の風 後 東の風 晴れ 時々 くもり 所により 昼過ぎ から 夕方 雨 で 雷を伴う","波 0.5メートル"],"rain":[{"timeZone":"00-06","time":0,"rainyPercent":""},{"timeZone":"06-12","time":6,"rainyPercent":""},{"timeZone":"12-18","time":12,"rainyPercent":20},{"timeZone":"18-24","time":18,"rainyPercent":10}],"temp":[{"city":"高松","min":"","max":35}]},{"date":"2019/7/30","dateJa":"明日30日","weather":"晴れ時々曇り","weatherCode":"101","info":["北の風 晴れ 時々 くもり 所により 昼過ぎ から 夕方 雨 で 雷を伴い 激しく 降る","波 0.5メートル"],"rain":[{"timeZone":"00-06","time":0,"rainyPercent":0},{"timeZone":"06-12","time":6,"rainyPercent":10},{"timeZone":"12-18","time":12,"rainyPercent":20},{"timeZone":"18-24","time":18,"rainyPercent":10}],"temp":[{"city":"高松","min":26,"max":33}]},{"date":"2019/7/31","dateJa":"明後日31日","weather":"晴れ時々曇り","weatherCode":"101","info":["北の風 晴れ 時々 くもり","波 0.5メートル"],"rain":[],"temp":[]}]}]}