{"id":"354","name":"大東島地方","caption":"6日17時南大東島地方気象台発表の天気予報(今日6日から明後日8日まで)","areas":[{"area":"大東島地方","forecast":[{"date":"2019/9/6","dateJa":"今夜6日","weather":"曇り","weatherCode":"200","info":["南の風 やや強く くもり 所により 夜 雨 で 雷を伴う","波 3メートル うねり を伴う"],"rain":[{"timeZone":"00-06","time":0,"rainyPercent":""},{"timeZone":"06-12","time":6,"rainyPercent":""},{"timeZone":"12-18","time":12,"rainyPercent":""},{"timeZone":"18-24","time":18,"rainyPercent":40}],"temp":[]},{"date":"2019/9/7","dateJa":"明日7日","weather":"曇り後時々晴れ","weatherCode":"210","info":["南の風 やや強く くもり 昼過ぎ から 時々 晴れ 所により 明け方 まで 雨 で 雷を伴う","波 3メートル 後 2.5メートル うねり を伴う"],"rain":[{"timeZone":"00-06","time":0,"rainyPercent":40},{"timeZone":"06-12","time":6,"rainyPercent":30},{"timeZone":"12-18","time":12,"rainyPercent":20},{"timeZone":"18-24","time":18,"rainyPercent":20}],"temp":[{"city":"南大東島","min":27,"max":32}]},{"date":"2019/9/8","dateJa":"明後日8日","weather":"曇り時々晴れ","weatherCode":"201","info":["南の風 くもり 時々 晴れ","波 2メートル うねり を伴う"],"rain":[],"temp":[]}]}]}